updatable/__init__.py
updatable/__main__.py
updatable/console.py
updatable/utils.py
updatable-0.7.1.dist-info/LICENSE
updatable-0.7.1.dist-info/METADATA
updatable-0.7.1.dist-info/WHEEL
updatable-0.7.1.dist-info/entry_points.txt
updatable-0.7.1.dist-info/top_level.txt
updatable-0.7.1.dist-info/RECORD
